README.md
setup.py
Utility_Function/AudioCapture.py
Utility_Function/BaseConversion.py
Utility_Function/CAPTCHA.py
Utility_Function/ClipBoard.py
Utility_Function/CodeString.py
Utility_Function/Email.py
Utility_Function/File.py
Utility_Function/GraytoChar.py
Utility_Function/HashValueString.py
Utility_Function/Image.py
Utility_Function/KeyBoard.py
Utility_Function/Mouse.py
Utility_Function/NetworkUtility.py
Utility_Function/Process.py
Utility_Function/Qrcode.py
Utility_Function/ScanFile.py
Utility_Function/ScreenShot.py
Utility_Function/System.py
Utility_Function/Time.py
Utility_Function/Video.py
Utility_Function/VideoCapture.py
Utility_Function/Web.py
Utility_Function/__init__.py
Utility_Function.egg-info/PKG-INFO
Utility_Function.egg-info/SOURCES.txt
Utility_Function.egg-info/dependency_links.txt
Utility_Function.egg-info/top_level.txt