Metadata-Version: 2.1
Name: Utility_Function
Version: 1.2.0
Summary: Utility_Function is a module designed to assist in Python programming. It defines several commonly used constants and functions, aimed at improving programming efficiency and code readability.
Author: fengwenxi
Author-email: yyxx1234567890q@dingtalk.com
Keywords: python,Utility,Function,Utility_Function,windows,mac,linux
Classifier: Development Status :: 4 - Beta
Classifier: Intended Audience :: Developers
Classifier: Programming Language :: Python :: 3
Classifier: License :: OSI Approved :: MIT License
Classifier: Operating System :: OS Independent
Requires-Python: >=3.6
